sptm/__init__.py
sptm/conditional.py
sptm/inference.py
sptm/model.py
sptm/postprocess.py
sptm/preprocess.py
sptm/utils.py
sptm-1.1.1.dist-info/LICENSE
sptm-1.1.1.dist-info/METADATA
sptm-1.1.1.dist-info/WHEEL
sptm-1.1.1.dist-info/top_level.txt
sptm-1.1.1.dist-info/RECORD
