Metadata-Version: 2.1
Name: sptm
Version: 1.1.1
Summary: Sentence Topic Prediction using Topic Modeling
Home-page: https://github.com/Rochan-A/sptm
Author: Rochan Avlur Venkat
Author-email: rochan170543@mechyd.ac.in
License: UNKNOWN
Platform: UNKNOWN
Classifier: Programming Language :: Python :: 3.7
Classifier: License :: OSI Approved :: MIT License
Classifier: Operating System :: OS Independent
Requires-Dist: gensim
Requires-Dist: sklearn
Requires-Dist: spacy
Requires-Dist: matplotlib
